{
  "$schema": "https://json-schema.org/draft/2020-12/schema",
  "$id": "tmp/github-publish/backlog_contract/draft_backlog_program_manifest_v1.schema.json",
  "title": "Draft Backlog Program Manifest v1",
  "type": "object",
  "required": [
    "program_code",
    "schema_version",
    "schema_path",
    "title",
    "generated_at",
    "count_snapshot",
    "policy_refs",
    "prerequisite_sequence",
    "recommended_sequence",
    "parallel_milestone_groups",
    "milestones"
  ],
  "properties": {
    "program_code": {
      "type": "string"
    },
    "schema_version": {
      "const": "draft-backlog-program-manifest-v1"
    },
    "schema_path": {
      "const": "tmp/github-publish/backlog_contract/draft_backlog_program_manifest_v1.schema.json"
    },
    "title": {
      "type": "string"
    },
    "generated_at": {
      "type": "string"
    },
    "count_snapshot": {
      "type": "string"
    },
    "policy_refs": {
      "type": "array",
      "items": {
        "type": "string"
      }
    },
    "prerequisite_sequence": {
      "type": "string"
    },
    "recommended_sequence": {
      "type": "string"
    },
    "parallel_milestone_groups": {
      "type": "array",
      "items": {
        "type": "array",
        "items": {
          "type": "string"
        }
      }
    },
    "milestones": {
      "type": "array",
      "items": {
        "type": "object",
        "required": [
          "code",
          "title",
          "domain",
          "priority",
          "publication_scope",
          "area_labels",
          "blocked_by_milestones",
          "issue_count",
          "issues"
        ],
        "properties": {
          "code": {
            "type": "string"
          },
          "title": {
            "type": "string"
          },
          "domain": {
            "type": "string"
          },
          "priority": {
            "type": "string"
          },
          "publication_scope": {
            "type": "string"
          },
          "area_labels": {
            "type": "array",
            "items": {
              "type": "string"
            }
          },
          "blocked_by_milestones": {
            "type": "array",
            "items": {
              "type": "string"
            }
          },
          "issue_count": {
            "type": "integer"
          },
          "issues": {
            "type": "array",
            "items": {
              "type": "object",
              "required": [
                "code",
                "title",
                "milestone_code",
                "publication_scope",
                "domain",
                "priority",
                "label_names",
                "blocked_by_milestones",
                "blocked_by_issue_codes",
                "direct_unblock_issue_codes",
                "kind",
                "body"
              ],
              "properties": {
                "code": {
                  "type": "string"
                },
                "title": {
                  "type": "string"
                },
                "milestone_code": {
                  "type": "string"
                },
                "publication_scope": {
                  "type": "string"
                },
                "domain": {
                  "type": "string"
                },
                "priority": {
                  "type": "string"
                },
                "label_names": {
                  "type": "array",
                  "items": {
                    "type": "string"
                  }
                },
                "blocked_by_milestones": {
                  "type": "array",
                  "items": {
                    "type": "string"
                  }
                },
                "blocked_by_issue_codes": {
                  "type": "array",
                  "items": {
                    "type": "string"
                  }
                },
                "direct_unblock_issue_codes": {
                  "type": "array",
                  "items": {
                    "type": "string"
                  }
                },
                "kind": {
                  "type": "string"
                },
                "body": {
                  "type": "string"
                }
              },
              "additionalProperties": false
            }
          }
        },
        "additionalProperties": false
      }
    }
  },
  "additionalProperties": false
}
